yating_tts_sdk/__init__.py
Yating_TTS_SDK-0.2.2.dist-info/LICENSE
Yating_TTS_SDK-0.2.2.dist-info/METADATA
Yating_TTS_SDK-0.2.2.dist-info/WHEEL
Yating_TTS_SDK-0.2.2.dist-info/top_level.txt
Yating_TTS_SDK-0.2.2.dist-info/RECORD
