Metadata-Version: 2.1
Name: Yating-TTS-SDK
Version: 0.2.2
Summary: Yating TTS SDK
Home-page: https://github.com/TaiwanAILabs-Yating/tts-sdk-python
Author: pinkeyu7
Author-email: pinke.yu7@gmail.com
Keywords: text to speech
Requires-Python: >=3.6
License-File: LICENSE
Requires-Dist: requests >=2.22.0
